thinqconnect/__init__.py
thinqconnect/const.py
thinqconnect/country.py
thinqconnect/device.py
thinqconnect/mqtt_client.py
thinqconnect/thinq_api.py
thinqconnect/devices/__init__.py
thinqconnect/devices/air_conditioner.py
thinqconnect/devices/air_purifier.py
thinqconnect/devices/air_purifier_fan.py
thinqconnect/devices/ceiling_fan.py
thinqconnect/devices/connect_device.py
thinqconnect/devices/const.py
thinqconnect/devices/cooktop.py
thinqconnect/devices/dehumidifier.py
thinqconnect/devices/dish_washer.py
thinqconnect/devices/dryer.py
thinqconnect/devices/home_brew.py
thinqconnect/devices/hood.py
thinqconnect/devices/humidifier.py
thinqconnect/devices/kimchi_refrigerator.py
thinqconnect/devices/microwave_oven.py
thinqconnect/devices/oven.py
thinqconnect/devices/plant_cultivator.py
thinqconnect/devices/refrigerator.py
thinqconnect/devices/robot_cleaner.py
thinqconnect/devices/stick_cleaner.py
thinqconnect/devices/styler.py
thinqconnect/devices/system_boiler.py
thinqconnect/devices/ventilator.py
thinqconnect/devices/washcombo.py
thinqconnect/devices/washcombo_main.py
thinqconnect/devices/washcombo_mini.py
thinqconnect/devices/washer.py
thinqconnect/devices/washtower.py
thinqconnect/devices/washtower_dryer.py
thinqconnect/devices/washtower_washer.py
thinqconnect/devices/water_heater.py
thinqconnect/devices/water_purifier.py
thinqconnect/devices/wine_cellar.py
thinqconnect/integration/__init__.py
thinqconnect/integration/homeassistant/__init__.py
thinqconnect/integration/homeassistant/api.py
thinqconnect/integration/homeassistant/property.py
thinqconnect/integration/homeassistant/specification.py
thinqconnect/integration/homeassistant/state.py
thinqconnect/integration/homeassistant/temperature.py
thinqconnect-1.0.8.dist-info/LICENSE
thinqconnect-1.0.8.dist-info/METADATA
thinqconnect-1.0.8.dist-info/WHEEL
thinqconnect-1.0.8.dist-info/top_level.txt
thinqconnect-1.0.8.dist-info/RECORD
