Metadata-Version: 2.1
Name: thinqconnect
Version: 1.0.8
Summary: ThinQ Connect Python SDK
Home-page: https://github.com/thinq-connect/pythinqconnect
Author: ThinQConnect
Author-email: thinq-connect@lge.com
Classifier: Programming Language :: Python :: 3
Classifier: License :: OSI Approved :: Apache Software License
Classifier: Operating System :: OS Independent
Classifier: Programming Language :: Python :: 3.10
Classifier: Programming Language :: Python :: 3.11
Requires-Python: >=3.10
License-File: LICENSE
Requires-Dist: aiohttp
Requires-Dist: awsiotsdk
Requires-Dist: pyOpenSSL
